{"cameraMode":{"drawMode":0,"name":"Shaded","section":"Shading Mode"},"sceneLighting":false,"audioPlay":false,"sceneViewState":{"m_AlwaysRefresh":false,"showFog":true,"showSkybox":false,"showFlares":true,"showImageEffects":true,"showParticleSystems":true,"showVisualEffectGraphs":true,"m_FxEnabled":true},"in2DMode":false,"pivot":{"x":0.0,"y":4.106858730316162,"z":21.89999771118164},"rotation":{"x":0.4890957176685333,"y":-0.08737196773290634,"z":0.049320414662361148,"w":0.8664414882659912},"size":48.4917106628418,"orthographic":false}